{"cameraMode":{"drawMode":0,"name":"Shaded","section":"Shading Mode"},"sceneLighting":false,"audioPlay":false,"sceneViewState":{"showFog":true,"showMaterialUpdate":false,"showSkybox":false,"showFlares":true,"showImageEffects":true,"showParticleSystems":true},"in2DMode":false,"pivot":{"x":-0.4874575138092041,"y":2.4827170372009279,"z":6.285207748413086},"rotation":{"x":0.039822060614824298,"y":0.9489506483078003,"z":-0.1335437297821045,"w":0.28297340869903567},"size":0.14146310091018678,"orthographic":false}